Workbook

Sheet Executive Summary
A1: ASTON INSURANCE GROUP - ROI ANALYSIS
A2: Interactive Financial Model - Adjust yellow cells to see impact
A4: KEY FINANCIAL METRICS
A5: Metric | B5: Value | C5: Notes
A6: Total Annual Savings Potential | B6: =Calculations!E22 -> 89268.2 | C6: Sum of all process savings
A7: Total Implementation Investment | B7: =Calculations!F22 -> 25400 | C7: One-time implementation cost
A8: Payback Period (months) | B8: =Calculations!G22 -> 3.4144298 | C8: Investment / Monthly savings
A9: First Year Net ROI | B9: =Calculations!E22-Calculations!F22 -> 63868.2 | C9: Savings minus investment
A10: ROI Percentage | B10: =(Calculations!E22-Calculations!F22)/Calculations!F22 -> 2.5144961 | C10: (Savings-Investment)/Investment
A11: 3-Year Cumulative Benefit | B11: =Calculations!E22*3-Calculations!F22-6000 -> 236404.6 | C11: Includes maintenance costs
A14: TOP PRIORITY RECOMMENDATIONS
A15: Rank | B15: Initiative | C15: Annual Savings | D15: Investment | E15: Payback
A16: 1 | B16: Policy Verification RPA | C16: =Calculations!E5 -> 13104 | D16: =Calculations!F5 -> 10000 | E16: =Calculations!G5 -> 9.1575092
A17: 2 | B17: Birthday Automation | C17: =Calculations!E8 -> 3375 | D17: =Calculations!F8 -> 650 | E17: =Calculations!G8 -> 2.3111111
A18: 3 | B18: Email Cross-Sell Campaigns | C18: =Calculations!E9 -> 24000 | D18: =Calculations!F9 -> 2000 | E18: =Calculations!G9 -> 1
A19: 4 | B19: Admin Task Automation | C19: =Calculations!E7 -> 19968 | D19: =Calculations!F7 -> 4250 | E19: =Calculations!G7 -> 2.5540865
A20: 5 | B20: Payment Follow-Up | C20: =Calculations!E6 -> 2059.2 | D20: =Calculations!F6 -> 1500 | E20: =Calculations!G6 -> 8.7412587
A23: HOW TO USE THIS MODEL
A24: 1. Go to the 'Assumptions' tab to adjust hourly rates, time estimates, and savings percentages
A25: 2. Yellow cells are inputs you can modify - changes automatically update all calculations
A26: 3. The 'Calculations' tab shows detailed ROI math for each process
A27: 4. The 'Implementation' tab shows the phased roadmap with costs
A28: 5. Return to this summary to see updated key metrics

Sheet Assumptions
A1: ADJUSTABLE ASSUMPTIONS
A2: Modify yellow cells to see impact on ROI calculations
A4: LABOR COSTS
A5: Role | B5: Hourly Rate | C5: Notes
A6: Admin Staff (Silvia, Yuliana, Mery) | B6: 26 | C6: FL/TX market rate for bilingual insurance admin
A7: Licensed Agents (Freddy, Andrea, Flor) | B7: 45 | C7: Includes commission opportunity cost
A10: TIME ESTIMATES (Hours/Month)
A11: Process | B11: Current Hours | C11: Period | D11: Notes
A12: Policy Verification (Peak) | B12: 160 | C12: Peak months (Jan-Feb) | D12: Mery 100% dedicated
A13: Policy Verification (Normal) | B13: 40 | C13: Normal months (Mar-Dec) | D13: Distributed across team
A14: Payment Follow-up | B14: 8.25 | C14: Monthly | D14: 62.5 clients × 6 min + list download
A15: Inbound Calls | B15: 113 | C15: Monthly | D15: Silvia 40% + Yuliana 40%
A16: Admin Tasks | B16: 160 | C16: Monthly | D16: Yuliana 80% + Silvia 20%
A17: Doc Request Tracking | B17: 22 | C17: Monthly | D17: 5 hrs/week overhead
A20: AUTOMATION SAVINGS PERCENTAGES
A21: Process | B21: Time Savings % | C21: Feasibility Score | D21: Notes
A22: Policy Verification | B22: 0.7 | C22: 7 | D22: RPA can automate 70% of checks
A23: Payment Follow-up | B23: 0.8 | C23: 9 | D23: Bulk SMS nearly eliminates manual work
A24: Inbound Calls | B24: 0.25 | C24: 5 | D24: IVR/self-service for simple queries
A25: Admin Tasks | B25: 0.4 | C25: 6 | D25: Templates and workflows
A26: Doc Request Tracking | B26: 0.75 | C26: 9 | D26: ZOHO workflow replaces Excel
A29: REVENUE GENERATION ASSUMPTIONS
A30: Initiative | B30: Value | C30: Unit | D30: Notes
A31: Birthday retention impact | B31: 0.0075 | C31: % improvement | D31: Conservative estimate
A32: Average client commission | B32: 150 | C32: Per client/year | D32: Blended ACA + ancillary
A33: Medicare conversion rate | B33: 0.4 | C33: % of eligible | D33: Industry standard
A34: Clients approaching 65/year | B34: 80 | C34: Count | D34: ~2.7% of 3,000 clients
A35: Medicare commission | B35: 400 | C35: Per policy | D35: Average first-year
A36: Cross-sell conversion rate | B36: 0.1 | C36: % of targeted | D36: Email campaign estimate
A37: Average ancillary commission | B37: 100 | C37: Per policy | D37: Dental/Vision/Life

Sheet Calculations
A1: DETAILED ROI CALCULATIONS
A3: Process | B3: Monthly Hours | C3: Annual Hours | D3: Annual Cost | E3: Annual Savings | F3: Implementation | G3: Payback (mo)
A5: Policy Verification | B5: =(Assumptions!B12*2+Assumptions!B13*10)/12 -> 60 | C5: =B5*12 -> 720 | D5: =C5*Assumptions!B6 -> 18720 | E5: =D5*Assumptions!B22 -> 13104 | F5: 10000 | G5: =F5/(E5/12) -> 9.1575092
A6: Payment Follow-up | B6: =Assumptions!B14 -> 8.25 | C6: =B6*12 -> 99 | D6: =C6*Assumptions!B6 -> 2574 | E6: =D6*Assumptions!B23 -> 2059.2 | F6: 1500 | G6: =F6/(E6/12) -> 8.7412587
A7: Admin Tasks | B7: =Assumptions!B16 -> 160 | C7: =B7*12 -> 1920 | D7: =C7*Assumptions!B6 -> 49920 | E7: =D7*Assumptions!B25 -> 19968 | F7: 4250 | G7: =F7/(E7/12) -> 2.5540865
A8: Birthday Automation | B8: 0 | C8: 0 | D8: 0 | E8: =Assumptions!B31*3000*Assumptions!B32 -> 3375 | F8: 650 | G8: =F8/(E8/12) -> 2.3111111
A9: Email Cross-Sell | B9: 0 | C9: 0 | D9: 0 | E9: =Assumptions!B36*2400*Assumptions!B37 -> 24000 | F9: 2000 | G9: =F9/(E9/12) -> 1
A10: Medicare Age Trigger | B10: 0 | C10: 0 | D10: 0 | E10: =Assumptions!B34*Assumptions!B33*Assumptions!B35 -> 12800 | F10: 1000 | G10: =F10/(E10/12) -> 0.9375
A11: Doc Request Tracking | B11: =Assumptions!B17 -> 22 | C11: =B11*12 -> 264 | D11: =C11*Assumptions!B6 -> 6864 | E11: =D11*Assumptions!B26 -> 5148 | F11: 1000 | G11: =F11/(E11/12) -> 2.3310023
A12: Inbound Call Optimization | B12: =Assumptions!B15 -> 113 | C12: =B12*12 -> 1356 | D12: =C12*Assumptions!B6 -> 35256 | E12: =D12*Assumptions!B24 -> 8814 | F12: 5000 | G12: =F12/(E12/12) -> 6.8073519
A22: TOTALS | B22: =SUM(B5:B12) -> 363.25 | C22: =SUM(C5:C12) -> 4359 | D22: =SUM(D5:D12) -> 113334 | E22: =SUM(E5:E12) -> 89268.2 | F22: =SUM(F5:F12) -> 25400 | G22: =F22/(E22/12) -> 3.4144298

Sheet Implementation
A1: IMPLEMENTATION ROADMAP
A3: PHASE 1: QUICK WINS (Month 1-2)
A4: Week | B4: Initiative | C4: Owner | D4: Cost (Low) | E4: Cost (High) | F4: Expected Outcome
A5: 1-2 | B5: SMS Consent Capture | C5: Admin | D5: 0 | E5: 0 | F5: Compliance foundation
A6: 1-2 | B6: Birthday Automation | C6: ZOHO Admin | D6: 500 | E6: 800 | F6: 250 touchpoints/month
A7: 2-3 | B7: Medicare Age Trigger | C7: ZOHO Admin | D7: 800 | E7: 1200 | F7: 5-8 qualified leads/month
A8: 3-4 | B8: Bulk SMS for Payments | C8: IT/Admin | D8: 1200 | E8: 1800 | F8: 80% time reduction
A9: 4-6 | B9: Doc Request Workflow | C9: Admin | D9: 800 | E9: 1200 | F9: Eliminate Excel tracking
A11: Phase 1 Total: | B11: =SUM(D5:D9) -> 3300 | C11: to | D11: =SUM(E5:E9) -> 5000
A14: PHASE 2: FOUNDATION BUILDING (Month 2-4)
A15: Week | B15: Initiative | C15: Owner | D15: Cost (Low) | E15: Cost (High) | F15: Expected Outcome
A16: 8-10 | B16: RingCentral-ZOHO Integration | C16: IT | D16: 1500 | E16: 2500 | F16: Call logging in CRM
A17: 8-12 | B17: Email Campaign Templates | C17: Marketing | D17: 800 | E17: 1200 | F17: 5-7 Spanish campaigns
A18: 10-12 | B18: Client Segmentation | C18: Admin | D18: 300 | E18: 300 | F18: Product-based segments
A19: 12-14 | B19: First Cross-Sell Campaign | C19: Marketing | D19: 200 | E19: 200 | F19: Target dental/vision
A20: 12-16 | B20: Admin Task Templates | C20: Admin | D20: 1000 | E20: 1000 | F20: Standardized workflows
A21: 14-16 | B21: Self-Service Portal | C21: IT | D21: 1500 | E21: 3000 | F21: ID requests online
A23: Phase 2 Total: | B23: =SUM(D16:D21) -> 5300 | C23: to | D23: =SUM(E16:E21) -> 8200
A26: PHASE 3: ADVANCED AUTOMATION (Month 4-6)
A27: Week | B27: Initiative | C27: Owner | D27: Cost (Low) | E27: Cost (High) | F27: Expected Outcome
A28: 16-20 | B28: Policy Verification RPA (Phase 1) | C28: IT/Vendor | D28: 4000 | E28: 6000 | F28: Health Sherpa automation
A29: 18-22 | B29: Policy Verification RPA (Phase 2) | C29: IT/Vendor | D29: 2500 | E29: 4500 | F29: Healthcare.gov automation
A30: 20-24 | B30: Advanced Reporting Dashboard | C30: IT | D30: 1000 | E30: 1500 | F30: Real-time KPIs
A31: 22-26 | B31: Renewal Campaign Automation | C31: Marketing | D31: 500 | E31: 500 | F31: 90-day advance reminders
A33: Phase 3 Total: | B33: =SUM(D28:D31) -> 8000 | C33: to | D33: =SUM(E28:E31) -> 12500
A36: GRAND TOTAL: | B36: =B11+B23+B33 -> 16600 | C36: to | D36: =D11+D23+D33 -> 25700

Sheet 3-Year Projection
A1: 3-YEAR FINANCIAL PROJECTION
A3: Year | B3: Investment | C3: Annual Savings | D3: Net Benefit | E3: Cumulative Benefit
A4: Year 1 | B4: =Calculations!F22 -> 25400 | C4: =Calculations!E22 -> 89268.2 | D4: =C4-B4 -> 63868.2 | E4: =D4 -> 63868.2
A5: Year 2 | B5: 3000 | C5: =Calculations!E22 -> 89268.2 | D5: =C5-B5 -> 86268.2 | E5: =D5+E4 -> 150136.4
A6: Year 3 | B6: 3000 | C6: =Calculations!E22 -> 89268.2 | D6: =C6-B6 -> 86268.2 | E6: =D6+E5 -> 236404.6
A8: 3-Year Total | B8: =SUM(B4:B6) -> 31400 | C8: =SUM(C4:C6) -> 267804.6 | D8: =SUM(D4:D6) -> 236404.6 | E8: =E6 -> 236404.6
A11: 3-Year ROI: | B11: =E8/B8 -> 7.5288089
